{"photos":{"page":1,"pages":1,"perpage":100,"total":6,"photo":[{"id":"51854983576","owner":"113235024@N05","secret":"75dba83c41","server":"65535","farm":66,"title":"Chrysuronia goudoti","ispublic":1,"isfriend":0,"isfamily":0},{"id":"50756122277","owner":"60395395@N02","secret":"7472771b27","server":"65535","farm":66,"title":"Shining-green hummingbird, Chrysuronia goudoti, Birding and nature tours COLOMBIA- Bogota Birding","ispublic":1,"isfriend":0,"isfamily":0},{"id":"50734960467","owner":"54249623@N08","secret":"ab39e932d5","server":"65535","farm":66,"title":"Colibr\u00ed de Goudot, Shining-green Hummingbird (Lepidopyga goudoti)","ispublic":1,"isfriend":0,"isfamily":0},{"id":"50734960282","owner":"54249623@N08","secret":"9aeb8df0bc","server":"65535","farm":66,"title":"Colibr\u00ed de Goudot, Shining-green Hummingbird (Lepidopyga goudoti)","ispublic":1,"isfriend":0,"isfamily":0},{"id":"35942360132","owner":"29170368@N03","secret":"0122035d3e","server":"65535","farm":66,"title":"Shining-green Hummingbird","ispublic":1,"isfriend":0,"isfamily":0},{"id":"52439721170","owner":"192502021@N07","secret":"2f9680fcdb","server":"65535","farm":66,"title":"Colibr\u00ed de Goudot Shining-green Hummingbird Chrysuronia goudoti-2","ispublic":1,"isfriend":0,"isfamily":0}]},"stat":"ok"}