{"photos":{"page":1,"pages":1,"perpage":100,"total":88,"photo":[{"id":"52096871859","owner":"96568982@N06","secret":"51170e291c","server":"65535","farm":66,"title":"ROCKFOWL, White-necked","ispublic":1,"isfriend":0,"isfamily":0},{"id":"51736426032","owner":"128578170@N06","secret":"34a86bebcf","server":"65535","farm":66,"title":"Yellow-headed Picathartes Picathartes gymnocephalus","ispublic":1,"isfriend":0,"isfamily":0},{"id":"51738133995","owner":"128578170@N06","secret":"dcd028a2a3","server":"65535","farm":66,"title":"Yellow-headed Picathartes Picathartes gymnocephalus","ispublic":1,"isfriend":0,"isfamily":0},{"id":"51562569598","owner":"125593628@N08","secret":"71e809445d","server":"65535","farm":66,"title":"White-necked Rockfowl (Picatharte de Guin\u00e9e) - Picathartes gymnocephalus","ispublic":1,"isfriend":0,"isfamily":0},{"id":"51563012179","owner":"125593628@N08","secret":"5e91e71f41","server":"65535","farm":66,"title":"White-necked Rockfowl (Picatharte de Guin\u00e9e) - Picathartes gymnocephalus","ispublic":1,"isfriend":0,"isfamily":0},{"id":"50919763321","owner":"119787485@N07","secret":"de374c698e","server":"65535","farm":66,"title":"White-necked Rockfowl (Picathartes gymnocephalus) - 20190305-07","ispublic":1,"isfriend":0,"isfamily":0},{"id":"49818171238","owner":"99613800@N02","secret":"6cf25b841b","server":"65535","farm":66,"title":"Picathartes gymnocephalus (White-necked Rockfowl) - Picathartidae - Bonkro, Ashanti Region, Ghana-2","ispublic":1,"isfriend":0,"isfamily":0},{"id":"49819017517","owner":"99613800@N02","secret":"e805b29fed","server":"65535","farm":66,"title":"Picathartes gymnocephalus (White-necked Rockfowl) - Picathartidae - Bonkro, Ashanti Region, Ghana-3","ispublic":1,"isfriend":0,"isfamily":0},{"id":"49818705921","owner":"99613800@N02","secret":"c2fe8426bd","server":"65535","farm":66,"title":"Picathartes gymnocephalus (White-necked Rockfowl) - Picathartidae - Bonkro, Ashanti Region, Ghana-5","ispublic":1,"isfriend":0,"isfamily":0},{"id":"49818169838","owner":"99613800@N02","secret":"7ce888df41","server":"65535","farm":66,"title":"Picathartes gymnocephalus (White-necked Rockfowl) - Picathartidae - Bonkro, Ashanti Region, Ghana-8","ispublic":1,"isfriend":0,"isfamily":0},{"id":"49818705311","owner":"99613800@N02","secret":"6db3d2aedb","server":"65535","farm":66,"title":"Picathartes gymnocephalus (White-necked Rockfowl) - Picathartidae - Bonkro, Ashanti Region, Ghana-4","ispublic":1,"isfriend":0,"isfamily":0},{"id":"49818704636","owner":"99613800@N02","secret":"c512886612","server":"65535","farm":66,"title":"Picathartes gymnocephalus (White-necked Rockfowl) - Picathartidae - Bonkro, Ashanti Region, Ghana-7","ispublic":1,"isfriend":0,"isfamily":0},{"id":"49818167618","owner":"99613800@N02","secret":"b9cb28fd48","server":"65535","farm":66,"title":"Picathartes gymnocephalus (White-necked Rockfowl) - Picathartidae - Bonkro, Ashanti Region, Ghana-9","ispublic":1,"isfriend":0,"isfamily":0},{"id":"49818702896","owner":"99613800@N02","secret":"b654af6e4a","server":"65535","farm":66,"title":"Picathartes gymnocephalus (White-necked Rockfowl) - Picathartidae - Bonkro, Ashanti Region, Ghana-10","ispublic":1,"isfriend":0,"isfamily":0},{"id":"49819013567","owner":"99613800@N02","secret":"0cd2a00ac5","server":"65535","farm":66,"title":"Picathartes gymnocephalus (White-necked Rockfowl) - Picathartidae - Bonkro, Ashanti Region, Ghana-6","ispublic":1,"isfriend":0,"isfamily":0},{"id":"49818701471","owner":"99613800@N02","secret":"1b0f8099de","server":"65535","farm":66,"title":"Picathartes gymnocephalus (White-necked Rockfowl) - Picathartidae - Bonkro, Ashanti Region, Ghana-11","ispublic":1,"isfriend":0,"isfamily":0},{"id":"49818701216","owner":"99613800@N02","secret":"981800dfcc","server":"65535","farm":66,"title":"Picathartes gymnocephalus (White-necked Rockfowl) - Picathartidae - Bonkro, Ashanti Region, Ghana-12","ispublic":1,"isfriend":0,"isfamily":0},{"id":"49419261567","owner":"146637507@N05","secret":"83d6555f98","server":"65535","farm":66,"title":"Picatarte collobianco (Picathartes gymnocephalus ) White-necked Rockfowl. Picatharte site, Ghana","ispublic":1,"isfriend":0,"isfamily":0},{"id":"49321750558","owner":"186211059@N06","secret":"41f1364794","server":"65535","farm":66,"title":"White-necked Rockfowl","ispublic":1,"isfriend":0,"isfamily":0},{"id":"40506325633","owner":"128578170@N06","secret":"b5d107d1a9","server":"7896","farm":8,"title":"Yellow-headed Picathartes Picathartes gymnocephalus","ispublic":1,"isfriend":0,"isfamily":0},{"id":"40506325183","owner":"128578170@N06","secret":"2317330769","server":"7823","farm":8,"title":"Yellow-headed Picathartes Picathartes gymnocephalus","ispublic":1,"isfriend":0,"isfamily":0},{"id":"40503811813","owner":"61827574@N03","secret":"ae19d97e80","server":"65535","farm":66,"title":"White-necked Rockfowl - Picathartes gymnocephalus","ispublic":1,"isfriend":0,"isfamily":0},{"id":"44431329160","owner":"61827574@N03","secret":"dd5e64ed64","server":"4821","farm":5,"title":"The White-necked Rockfowl (Picarthartes) is a large and unusual bird with a bright chrome yellow and black featherless head and a long neck and tail. It is classified as vulnerable and considered one of Africa\u2019s most desirable birds by birders","ispublic":1,"isfriend":0,"isfamily":0},{"id":"27248072698","owner":"128578170@N06","secret":"a63b6c50af","server":"881","farm":1,"title":"Yellow-headed Picathartes Picathartes gymnocephalus","ispublic":1,"isfriend":0,"isfamily":0},{"id":"39312100610","owner":"128578170@N06","secret":"e888824444","server":"791","farm":1,"title":"Yellow-headed Picathartes Picathartes gymnocephalus","ispublic":1,"isfriend":0,"isfamily":0},{"id":"27248072578","owner":"128578170@N06","secret":"99e35131ef","server":"891","farm":1,"title":"Yellow-headed Picathartes Picathartes gymnocephalus","ispublic":1,"isfriend":0,"isfamily":0},{"id":"40033841162","owner":"11590393@N05","secret":"0ccf9aecd5","server":"4615","farm":5,"title":"White-necked Picathartes (Picathartes gymnocephalus)","ispublic":1,"isfriend":0,"isfamily":0},{"id":"38459547654","owner":"12639178@N07","secret":"d6bc8b7142","server":"4597","farm":5,"title":"Gelbkopf-Felsh\u00fcpfer, Yellow-headed Picathartes (Picathartes gymnocephalus) , NGIDn920071745","ispublic":1,"isfriend":0,"isfamily":0},{"id":"27389849159","owner":"12639178@N07","secret":"acf4ef8999","server":"4635","farm":5,"title":"Gelbkopf-Felsh\u00fcpfer, Yellow-headed Picathartes (Picathartes gymnocephalus) , NGIDn1911974928","ispublic":1,"isfriend":0,"isfamily":0},{"id":"25065203098","owner":"12639178@N07","secret":"20afbfc4b8","server":"4585","farm":5,"title":"Gelbkopf-Felsh\u00fcpfer, Yellow-headed Picathartes (Picathartes gymnocephalus) , NGIDn1921171880","ispublic":1,"isfriend":0,"isfamily":0},{"id":"38936920871","owner":"12639178@N07","secret":"0ab518149b","server":"4643","farm":5,"title":"Gelbkopf-Felsh\u00fcpfer, Yellow-headed Picathartes (Picathartes gymnocephalus) , NGID1809901451","ispublic":1,"isfriend":0,"isfamily":0},{"id":"38936917171","owner":"12639178@N07","secret":"af1481394f","server":"4549","farm":5,"title":"Gelbkopf-Felsh\u00fcpfer, Yellow-headed Picathartes (Picathartes gymnocephalus) , NGID144624768","ispublic":1,"isfriend":0,"isfamily":0},{"id":"24071916257","owner":"12639178@N07","secret":"11fc24de27","server":"4559","farm":5,"title":"Gelbkopf-Felsh\u00fcpfer, Yellow-headed Picathartes (Picathartes gymnocephalus) , NGID1125021381","ispublic":1,"isfriend":0,"isfamily":0},{"id":"33566868174","owner":"129673089@N03","secret":"b797422a2d","server":"65535","farm":66,"title":"White-necked rockfowl, Picathartes gymnocephalus","ispublic":1,"isfriend":0,"isfamily":0},{"id":"33246017700","owner":"128578170@N06","secret":"024a4d76a8","server":"2812","farm":3,"title":"Yellow-headed Picathartes Picathartes gymnocephalus","ispublic":1,"isfriend":0,"isfamily":0},{"id":"32309825514","owner":"64045479@N05","secret":"130fa81ce1","server":"578","farm":1,"title":"White-necked Rockfowl - Picathartes gymnocephalus","ispublic":1,"isfriend":0,"isfamily":0},{"id":"32772143550","owner":"64045479@N05","secret":"f067627bb8","server":"3776","farm":4,"title":"White-necked Rockfowl - Picathartes gymnocephalus","ispublic":1,"isfriend":0,"isfamily":0},{"id":"31665978834","owner":"97870575@N08","secret":"2a02d025c8","server":"480","farm":1,"title":"Picathartes gymnocephalus","ispublic":1,"isfriend":0,"isfamily":0},{"id":"23844925351","owner":"37347725@N07","secret":"b1e6bca3f1","server":"5685","farm":6,"title":"Yellow-headed Picarthartes, White-necked Rockfowl,   Picathartes gymnocephalus","ispublic":1,"isfriend":0,"isfamily":0},{"id":"23269497214","owner":"22333182@N04","secret":"4c23fa60dc","server":"5626","farm":6,"title":"White-necked Rockfowl Picathartes gymnocephalus","ispublic":1,"isfriend":0,"isfamily":0},{"id":"23511610301","owner":"76617062@N08","secret":"51f61ea588","server":"587","farm":1,"title":"1.19280 Picatharte de Guin\u00e9e \/ Picathartes gymnocephalus \/ White-necked Rockfowl","ispublic":1,"isfriend":0,"isfamily":0},{"id":"22845344037","owner":"7330431@N08","secret":"80bd0eca95","server":"5633","farm":6,"title":"White-necked Picathartes Picathartes gymnocephalus","ispublic":1,"isfriend":0,"isfamily":0},{"id":"23239496115","owner":"7330431@N08","secret":"9b1038f7d9","server":"754","farm":1,"title":"White-necked Picathartes Picathartes gymnocephalus","ispublic":1,"isfriend":0,"isfamily":0},{"id":"19170517952","owner":"61021753@N02","secret":"fafa86e0b4","server":"3946","farm":4,"title":"n42_w1150","ispublic":1,"isfriend":0,"isfamily":0},{"id":"16202947572","owner":"30818542@N04","secret":"03e1054599","server":"7567","farm":8,"title":"Yellow-headed Picathartes - Ghana 14_S4E2922","ispublic":1,"isfriend":0,"isfamily":0},{"id":"15186794140","owner":"72217703@N05","secret":"cac2b7ce87","server":"2942","farm":3,"title":"Picathartes gymnocephalus - Kelkarga (video)","ispublic":1,"isfriend":0,"isfamily":0},{"id":"11803979536","owner":"62877922@N08","secret":"e31c30c1d0","server":"7362","farm":8,"title":"Yellow-headed Rockfowl (Picathartes gymnocephalus)","ispublic":1,"isfriend":0,"isfamily":0},{"id":"11803215775","owner":"62877922@N08","secret":"88f808f936","server":"7399","farm":8,"title":"Yellow-headed Rockfowl (Picathartes gymnocephalus)","ispublic":1,"isfriend":0,"isfamily":0},{"id":"11114227294","owner":"25753251@N03","secret":"af2f36df90","server":"2834","farm":3,"title":"White-necked Rockfowl (Yellow-headed Picathartes)","ispublic":1,"isfriend":0,"isfamily":0},{"id":"10697119936","owner":"72217703@N05","secret":"3f9d008c6f","server":"5503","farm":6,"title":"Picathartes gymnocephalus - Kelkarga, Kayatavu\u011fu","ispublic":1,"isfriend":0,"isfamily":0},{"id":"10330114394","owner":"61021753@N02","secret":"8d2881c1a9","server":"2820","farm":3,"title":"n211_w1150","ispublic":1,"isfriend":0,"isfamily":0},{"id":"8024413341","owner":"48592979@N06","secret":"76776fedcc","server":"8181","farm":9,"title":"Yellow-headed Picathartes (Picathartes gymnocephalus)","ispublic":1,"isfriend":0,"isfamily":0},{"id":"6336835591","owner":"36279497@N05","secret":"643617030b","server":"6239","farm":7,"title":"White-necked Rockfowl (Picathartes gymnocephalus)","ispublic":1,"isfriend":0,"isfamily":0},{"id":"5946137440","owner":"27651543@N08","secret":"156055bb67","server":"6024","farm":7,"title":"Picathartes gymnocephalus - White-necked Picathartes","ispublic":1,"isfriend":0,"isfamily":0},{"id":"3791590679","owner":"36279497@N05","secret":"6f7daa205a","server":"2568","farm":3,"title":"Picathartes gymnocephalus","ispublic":1,"isfriend":0,"isfamily":0},{"id":"504242292","owner":"8112828@N03","secret":"39d161fc26","server":"218","farm":1,"title":"Picathartes gymnocephalus","ispublic":1,"isfriend":0,"isfamily":0},{"id":"378232845","owner":"78445114@N00","secret":"e752576b7a","server":"169","farm":1,"title":"White-necked Rockfowl","ispublic":1,"isfriend":0,"isfamily":0},{"id":"52096661098","owner":"96568982@N06","secret":"b1f3d057b5","server":"65535","farm":66,"title":"ROCKFOWL, White-necked","ispublic":1,"isfriend":0,"isfamily":0},{"id":"52009142513","owner":"186211059@N06","secret":"7f42a73e16","server":"65535","farm":66,"title":"White-necked Rockfowl","ispublic":1,"isfriend":0,"isfamily":0},{"id":"52009600640","owner":"186211059@N06","secret":"1243662984","server":"65535","farm":66,"title":"White-necked Rockfowl","ispublic":1,"isfriend":0,"isfamily":0},{"id":"51738134055","owner":"128578170@N06","secret":"e4b63a3aa1","server":"65535","farm":66,"title":"Yellow-headed Picathartes Picathartes gymnocephalus","ispublic":1,"isfriend":0,"isfamily":0},{"id":"50268373236","owner":"142952595@N08","secret":"5844592921","server":"65535","farm":66,"title":"White-necked Rockfowl (Picathartes)","ispublic":1,"isfriend":0,"isfamily":0},{"id":"50267710973","owner":"142952595@N08","secret":"dd3bf57d59","server":"65535","farm":66,"title":"White-necked Rockfowl (Picathartes)","ispublic":1,"isfriend":0,"isfamily":0},{"id":"50268549507","owner":"142952595@N08","secret":"d1d81f5426","server":"65535","farm":66,"title":"White-necked Rockfowl (Picathartes)","ispublic":1,"isfriend":0,"isfamily":0},{"id":"50267710718","owner":"142952595@N08","secret":"0674086cf4","server":"65535","farm":66,"title":"White-necked Rockfowl (Picathartes)","ispublic":1,"isfriend":0,"isfamily":0},{"id":"40506326373","owner":"128578170@N06","secret":"feaa5ced4c","server":"7884","farm":8,"title":"Yellow-headed Picathartes Picathartes gymnocephalus","ispublic":1,"isfriend":0,"isfamily":0},{"id":"28287037489","owner":"11590393@N05","secret":"0e9cb7bb29","server":"4620","farm":5,"title":"White-necked Picathartes (Picathartes gymnocephalus)","ispublic":1,"isfriend":0,"isfamily":0},{"id":"28287037279","owner":"11590393@N05","secret":"1415260ff8","server":"4713","farm":5,"title":"White-necked Picathartes (Picathartes gymnocephalus)","ispublic":1,"isfriend":0,"isfamily":0},{"id":"40066571701","owner":"11590393@N05","secret":"5393422f00","server":"4706","farm":5,"title":"White-necked Picathartes (Picathartes gymnocephalus)","ispublic":1,"isfriend":0,"isfamily":0},{"id":"39136927042","owner":"12639178@N07","secret":"44e47ae735","server":"4685","farm":5,"title":"Gelbkopf-Felsh\u00fcpfer, Yellow-headed Picathartes (Picathartes gymnocephalus) , NGIDn1499851254","ispublic":1,"isfriend":0,"isfamily":0},{"id":"39136916162","owner":"12639178@N07","secret":"a9b73a86ca","server":"4687","farm":5,"title":"Gelbkopf-Felsh\u00fcpfer, Yellow-headed Picathartes (Picathartes gymnocephalus) , NGID440680732","ispublic":1,"isfriend":0,"isfamily":0},{"id":"27389840539","owner":"12639178@N07","secret":"63711ac2aa","server":"4679","farm":5,"title":"Gelbkopf-Felsh\u00fcpfer, Yellow-headed Picathartes (Picathartes gymnocephalus) , NGID888354120","ispublic":1,"isfriend":0,"isfamily":0},{"id":"33246017480","owner":"128578170@N06","secret":"a410bfdb58","server":"3710","farm":4,"title":"Yellow-headed Picathartes Picathartes gymnocephalus","ispublic":1,"isfriend":0,"isfamily":0},{"id":"31794015710","owner":"128578170@N06","secret":"040cb8f98e","server":"350","farm":1,"title":"Yellow-headed Picathartes Picathartes gymnocephalus","ispublic":1,"isfriend":0,"isfamily":0},{"id":"22871529239","owner":"7330431@N08","secret":"def3f6b489","server":"638","farm":1,"title":"White-necked Picathartes Picathartes gymnocephalus","ispublic":1,"isfriend":0,"isfamily":0},{"id":"11803980426","owner":"62877922@N08","secret":"2bc2e1425f","server":"5520","farm":6,"title":"Yellow-headed Rockfowl (Picathartes gymnocephalus)","ispublic":1,"isfriend":0,"isfamily":0},{"id":"11352238493","owner":"57465751@N05","secret":"19ffee3577","server":"7326","farm":8,"title":"Yellow-headed Picathartes (Picathartes gymnocephalus), Bonkro, Ghana 11\/9\/13","ispublic":1,"isfriend":0,"isfamily":0},{"id":"10140824803","owner":"60188113@N04","secret":"8c76891309","server":"2890","farm":3,"title":"White-necked Picathartes","ispublic":1,"isfriend":0,"isfamily":0},{"id":"9359741066","owner":"99314705@N05","secret":"acfea2820c","server":"3810","farm":4,"title":"Picathartes gymnocephalus","ispublic":1,"isfriend":0,"isfamily":0},{"id":"5945580793","owner":"27651543@N08","secret":"6bc804a2e4","server":"6128","farm":7,"title":"Picathartes gymnocephalus - White-necked Picathartes","ispublic":1,"isfriend":0,"isfamily":0},{"id":"3792403406","owner":"36279497@N05","secret":"c0116cce0c","server":"2467","farm":3,"title":"Picathartes gymnocephalus","ispublic":1,"isfriend":0,"isfamily":0},{"id":"3791590263","owner":"36279497@N05","secret":"ed3e843f67","server":"3453","farm":4,"title":"Picathartes gymnocephalus","ispublic":1,"isfriend":0,"isfamily":0},{"id":"3792402588","owner":"36279497@N05","secret":"702651c459","server":"3457","farm":4,"title":"Picathartes gymnocephalus","ispublic":1,"isfriend":0,"isfamily":0},{"id":"3792402254","owner":"36279497@N05","secret":"59c5221827","server":"3581","farm":4,"title":"Picathartes gymnocephalus","ispublic":1,"isfriend":0,"isfamily":0},{"id":"3792401652","owner":"36279497@N05","secret":"ebee184b30","server":"3553","farm":4,"title":"Picathartes gymnocephalus","ispublic":1,"isfriend":0,"isfamily":0},{"id":"3791588543","owner":"36279497@N05","secret":"1c50ea1842","server":"2530","farm":3,"title":"Picathartes gymnocephalus","ispublic":1,"isfriend":0,"isfamily":0},{"id":"3792400952","owner":"36279497@N05","secret":"03d0ac1c7a","server":"2487","farm":3,"title":"Picathartes gymnocephalus","ispublic":1,"isfriend":0,"isfamily":0},{"id":"3791587915","owner":"36279497@N05","secret":"ed05bd4d06","server":"2464","farm":3,"title":"Picathartes gymnocephalus","ispublic":1,"isfriend":0,"isfamily":0}]},"stat":"ok"}